agentmanager/__init__.py
agentmanager/manager.py
agentmanager/ui.py
agentmanager/ui_launcher.py
agentmanager/config/__init__.py
agentmanager/config/model_config.py
agentmanager-0.1.1.dist-info/METADATA
agentmanager-0.1.1.dist-info/WHEEL
agentmanager-0.1.1.dist-info/entry_points.txt
agentmanager-0.1.1.dist-info/top_level.txt
agentmanager-0.1.1.dist-info/RECORD
