Metadata-Version: 2.4
Name: AgentManager
Version: 0.1.1
Summary: Managing a unified ecosystem of LLM providers, agents, and MCP servers.
Author: Nilavo Boral
Author-email: nilavoboral@gmail.com
Project-URL: LinkedIn, https://www.linkedin.com/in/nilavo-boral-123bb5228/
Classifier: Programming Language :: Python :: 3.11
Classifier: License :: OSI Approved :: MIT License
Classifier: Operating System :: OS Independent
Requires-Python: >=3.11
Requires-Dist: langchain==1.0.5
Requires-Dist: langchain-core==1.0.4
Requires-Dist: langchain-mcp-adapters==0.1.12
Requires-Dist: langchain-google-genai==3.0.1
Requires-Dist: langchain-openai==1.0.2
Requires-Dist: langchain-groq==1.0.0
Requires-Dist: langchain-mistralai==1.0.1
Requires-Dist: langchain-ollama==1.0.0
Requires-Dist: nest_asyncio==1.6.0
Provides-Extra: ui
Requires-Dist: streamlit==1.49.1; extra == "ui"
Dynamic: author
Dynamic: author-email
Dynamic: classifier
Dynamic: description
Dynamic: description-content-type
Dynamic: project-url
Dynamic: provides-extra
Dynamic: requires-dist
Dynamic: requires-python
Dynamic: summary
